komputee/__init__.py
komputee/komputee.py
komputee-0.0.9.dist-info/METADATA
komputee-0.0.9.dist-info/WHEEL
komputee-0.0.9.dist-info/licenses/LICENSE
komputee-0.0.9.dist-info/RECORD
